scalar_django_ninja/__init__.py
scalar_django_ninja/scalar_django_ninja.py
scalar_django_ninja-0.1.4.dist-info/METADATA
scalar_django_ninja-0.1.4.dist-info/WHEEL
scalar_django_ninja-0.1.4.dist-info/RECORD
