Metadata-Version: 2.3
Name: scalar-django-ninja
Version: 0.1.4
Summary: 
Author: Gpocas
Author-email: gpocas01@gmail.com
Requires-Python: >=3.12
Classifier: Topic :: Software Development :: Build Tools
Classifier: Topic :: Software Development :: Libraries :: Python Modules
Classifier: Natural Language :: Portuguese (Brazilian)
Classifier: Development Status :: 5 - Production/Stable
Classifier: Programming Language :: Python :: 3.12
Requires-Dist: django-ninja (>=1.4.3,<2.0.0)
Requires-Dist: typing-extensions (>=4.14.0,<5.0.0)
Project-URL: Bug Tracker, https://github.com/Gpocas/scalar_django_ninja/issues
Project-URL: Repository, https://github.com/Gpocas/scalar_django_ninja
